brewerwall/__init__.py
brewerwall/beercalc.py
brewerwall/cli.py
brewerwall-0.3.1.dist-info/AUTHORS.rst
brewerwall-0.3.1.dist-info/LICENSE
brewerwall-0.3.1.dist-info/METADATA
brewerwall-0.3.1.dist-info/WHEEL
brewerwall-0.3.1.dist-info/entry_points.txt
brewerwall-0.3.1.dist-info/top_level.txt
brewerwall-0.3.1.dist-info/RECORD
