Metadata-Version: 2.1
Name: brewerwall
Version: 0.3.1
Summary: A collection of tools, data and programming resources for all of your beer needs!
Home-page: https://github.com/dmofot/brewerwall
Author: David Todd
Author-email: dmofot@gmail.com
License: GNU General Public License v3
Keywords: brewerwall
Platform: UNKNOWN
Classifier: Development Status :: 2 - Pre-Alpha
Classifier: Intended Audience :: Developers
Classifier: License :: OSI Approved :: GNU General Public License v3 (GPLv3)
Classifier: Natural Language :: English
Classifier: Programming Language :: Python :: 3
Classifier: Programming Language :: Python :: 3.4
Classifier: Programming Language :: Python :: 3.5
Classifier: Programming Language :: Python :: 3.6
Classifier: Programming Language :: Python :: 3.7
Requires-Dist: Click (>=6.0)
